pytest_dbt_conventions/__init__.py
pytest_dbt_conventions/plugin.py
pytest_dbt_conventions-0.1.2.dist-info/entry_points.txt
pytest_dbt_conventions-0.1.2.dist-info/LICENSE
pytest_dbt_conventions-0.1.2.dist-info/WHEEL
pytest_dbt_conventions-0.1.2.dist-info/METADATA
pytest_dbt_conventions-0.1.2.dist-info/RECORD
